{"qH9ahkduI+mqg8WEnveKGQ==":"mbr-1920x1080.jpg","vsPgUZy1HrIRqmxzJ0vufQ==":"vova_i_nastja__5_3_weddywood-960x640.jpg","km68HyU1WFQwgXov6MIngg==":"logo2.png","UtELI0Eov/Uu0hRaxAuCNg==":"logo2-1.png","h4KvhsHObXinV5jwTFkUyw==":"images%20(1)-253x199.jpg","hqmQGYFXHkwa3t0EjLVjcA==":"images%20(2)-300x168.jpg","jbClELBqOxP0Tol/jyE0ew==":"%D0%91%D0%B5%D0%B7%20%D0%BD%D0%B0%D0%B7%D0%B2%D0%B0%D0%BD%D0%B8%D1%8F%20(1)-225x225.jpg","7BTA4NKRLSScrveu0IgaOw==":"images-286x176.jpg","qFea5mff3o1B/Qeb88hL1w==":"images%20(6)-278x181.jpg","BY1bFbFssb0aXRFZj0+4bw==":"%D0%91%D0%B5%D0%B7%20%D0%BD%D0%B0%D0%B7%D0%B2%D0%B0%D0%BD%D0%B8%D1%8F%20(2)-225x225.jpg","RFtFCZuRTnI/hv+S4ZNz4A==":"%D0%91%D0%B5%D0%B7%20%D0%BD%D0%B0%D0%B7%D0%B2%D0%B0%D0%BD%D0%B8%D1%8F%20(4)-183x275.jpg","506cxYeC4gWs2WBnvqoe9A==":"images%20(3)-194x259.jpg","xodsn0Suzmud8UUuha7YSg==":"dk6xala2fqyfk8ptdb0cupjj2kcbyti3z8dy-600x370.jpg","SSx8zNmCnyZyNzy+8nuutA==":"%D0%91%D0%B5%D0%B7%20%D0%BD%D0%B0%D0%B7%D0%B2%D0%B0%D0%BD%D0%B8%D1%8F%20(3)-225x225.jpg","5qj4+joPW0L9c8I9h4Rdxw==":"images%20(7)-225x225.jpg","RW8cgl9GgLarbbUkzMrNPA==":"images%20(1)-225x225.png"}